[{"id":"shop-ky-wilmore-hrs-automotive","name":"HRS Automotive","slug":"ky-wilmore-hrs-automotive","lat":37.8623161,"lng":-84.657328,"state":"KY","city":"Wilmore","address":"102 Tococo Court","zip":"40390","phone":"","email":"","website":"","hours":"Mo-Fr 8:00-17:00","brand":"","services":["general_repair"],"shopType":"general_repair"},{"id":"shop-ky-lexington-auto-excel","name":"Auto Excel","slug":"ky-lexington-auto-excel","lat":38.0013862,"lng":-84.5292439,"state":"KY","city":"lexington","address":"271 Gold Rush Road","zip":"40503","phone":"","email":"","website":"","hours":"Mo-Fr 08:00-17:00","brand":"","services":["general_repair"],"shopType":"general_repair"},{"id":"shop-ky-lexington-abe-s-auto-repair-new-location","name":"Abe's Auto Repair New Location","slug":"ky-lexington-abe-s-auto-repair-new-location","lat":38.0012336,"lng":-84.5286285,"state":"KY","city":"Lexington","address":"271 Gold Rush Road","zip":"40503","phone":"","email":"","website":"","hours":"","brand":"","services":["general_repair"],"shopType":"general_repair"},{"id":"shop-ky-shively-rockford-automotive","name":"Rockford Automotive","slug":"ky-shively-rockford-automotive","lat":38.1760744,"lng":-85.8272265,"state":"KY","city":"Shively","address":"4757 Rockford Plaza","zip":"40216","phone":"","email":"","website":"","hours":"","brand":"","services":["general_repair"],"shopType":"general_repair"},{"id":"shop-ky-lexington-alliance-tire-company","name":"Alliance Tire Company","slug":"ky-lexington-alliance-tire-company","lat":37.9980638,"lng":-84.5469096,"state":"KY","city":"Lexington","address":"3306 Clays Mill Road","zip":"","phone":"","email":"","website":"","hours":"","brand":"Alliance","services":["tires"],"shopType":"tire_shop"},{"id":"shop-ky-lexington-valvoline-instant-oil-change","name":"Valvoline Instant Oil Change","slug":"ky-lexington-valvoline-instant-oil-change","lat":38.0063966,"lng":-84.5732131,"state":"KY","city":"Lexington","address":"3792 Palomar Centre Drive","zip":"","phone":"","email":"","website":"https://store.vioc.com/ky/lexington/oil-change-040024.html","hours":"","brand":"Valvoline","services":["oil_change"],"shopType":"quick_lube"},{"id":"shop-ky-lexington-lexington-lifted","name":"Lexington lifted","slug":"ky-lexington-lexington-lifted","lat":38.0219548,"lng":-84.4523605,"state":"KY","city":"Lexington","address":"2340;2342 Palumbo Drive","zip":"","phone":"","email":"","website":"","hours":"","brand":"","services":["general_repair"],"shopType":"general_repair"},{"id":"shop-ky-lexington-honda-repair-and-service","name":"Honda Repair and Service","slug":"ky-lexington-honda-repair-and-service","lat":38.0215243,"lng":-84.4522189,"state":"KY","city":"Lexington","address":"429 Codell Drive","zip":"","phone":"","email":"","website":"","hours":"","brand":"Honda","services":["car_repair"],"shopType":"general_repair"},{"id":"shop-ky-corbin-bolton-s-towing-repair","name":"Bolton's Towing & Repair","slug":"ky-corbin-bolton-s-towing-repair","lat":36.9661022,"lng":-84.082804,"state":"KY","city":"Corbin","address":"235 West Cumberland Gap Parkway","zip":"40701","phone":"+1-606-523-1132","email":"","website":"http://boltonstowingandrepair.com","hours":"","brand":"","services":["general_repair"],"shopType":"general_repair"},{"id":"shop-ky-nicholasville-lyons-auto-body","name":"Lyons Auto Body","slug":"ky-nicholasville-lyons-auto-body","lat":37.8908725,"lng":-84.5890894,"state":"KY","city":"Nicholasville","address":"246 Wilson Drive","zip":"40356","phone":"+1 859-885-1913","email":"","website":"https://www.lyonsautobodyky.com","hours":"","brand":"","services":["body_work"],"shopType":"body_shop"},{"id":"shop-ky-paris-mechanic-masters-llc","name":"Mechanic Masters, LLC","slug":"ky-paris-mechanic-masters-llc","lat":38.1999777,"lng":-84.2685469,"state":"KY","city":"Paris","address":"40 West 20th Street","zip":"40361","phone":"+1-859-987-2407","email":"","website":"https://mechanicmastersllc.com/","hours":"","brand":"","services":["general_repair"],"shopType":"general_repair"},{"id":"shop-ky-louisville-gap-automotive-exhaust","name":"GAP Automotive & Exhaust","slug":"ky-louisville-gap-automotive-exhaust","lat":38.1477918,"lng":-85.6913129,"state":"KY","city":"Louisville","address":"7115 Preston Highway","zip":"40219","phone":"+1-502-968-6128","email":"","website":"http://louisvilleautoshop.com","hours":"Mo-Fr 09:00-18:00; Sa 09:00-15:00","brand":"","services":["exhaust"],"shopType":"general_repair"},{"id":"shop-ky-louisville-east-end-auto-import-service","name":"East End Auto Import Service","slug":"ky-louisville-east-end-auto-import-service","lat":38.2527851,"lng":-85.7032876,"state":"KY","city":"Louisville","address":"2258 Frankfort Avenue","zip":"40206","phone":"+1 502 896 6061","email":"","website":"","hours":"","brand":"","services":["general_repair"],"shopType":"general_repair"},{"id":"shop-ky-florence-rider-s-automotive-llc","name":"Rider's Automotive, LLC","slug":"ky-florence-rider-s-automotive-llc","lat":38.9562053,"lng":-84.6211052,"state":"KY","city":"Florence","address":"10057 Dixie Highway","zip":"41042","phone":"+1-859-371-1090","email":"","website":"","hours":"Mo-Fr 08:00-18:00","brand":"","services":["truck_repair","car_repair","oil_change","air_conditioning","tyres","diagnostics","tires","brakes","muffler","batteries","inspection","exhaust","alignment"],"shopType":"general_repair"},{"id":"shop-ky-london-a-shade-darker","name":"A Shade Darker","slug":"ky-london-a-shade-darker","lat":37.105961,"lng":-84.0828472,"state":"KY","city":"London","address":"605 West Highway 192","zip":"40741","phone":"+1-606-770-5155","email":"","website":"https://www.ashadedarkeronline.com","hours":"Tu-Sa 08:00-17:00","brand":"","services":["window_tinting"],"shopType":"general_repair"},{"id":"shop-ky-alexandria-community-car-care","name":"Community Car Care","slug":"ky-alexandria-community-car-care","lat":38.9423627,"lng":-84.3925953,"state":"KY","city":"Alexandria","address":"1047 Perkins Drive","zip":"41001","phone":"+1-859-635-1788","email":"","website":"https://www.communitycarcareky.com","hours":"Mo-Fr 08:00-17:00","brand":"","services":["general_repair"],"shopType":"general_repair"},{"id":"shop-ky-winchester-5-star-exhaust-auto-repair","name":"5 Star Exhaust & Auto Repair","slug":"ky-winchester-5-star-exhaust-auto-repair","lat":37.994641,"lng":-84.1746799,"state":"KY","city":"Winchester","address":"East Washington Street","zip":"40391","phone":"+1-859-744-4054","email":"","website":"https://5starexhaustautorepair.com","hours":"Mo-Fr 07:30-17:00","brand":"","services":["tuning","engine_repair","exhaust","brakes"],"shopType":"general_repair"},{"id":"shop-ky-louisville-conn-s-auto-service","name":"Conn's Auto Service","slug":"ky-louisville-conn-s-auto-service","lat":38.2243382,"lng":-85.691358,"state":"KY","city":"Louisville","address":"2251 Bardstown Road","zip":"40205","phone":"","email":"","website":"","hours":"","brand":"","services":["general_repair"],"shopType":"general_repair"},{"id":"shop-ky-louisville-conn-s-body-shop","name":"Conn's Body Shop","slug":"ky-louisville-conn-s-body-shop","lat":38.2245063,"lng":-85.6916433,"state":"KY","city":"Louisville","address":"2247 Bardstown Road","zip":"40205","phone":"","email":"","website":"","hours":"","brand":"","services":["body_work"],"shopType":"body_shop"},{"id":"shop-ky-corbin-bill-morgan-tire-company","name":"Bill Morgan Tire Company","slug":"ky-corbin-bill-morgan-tire-company","lat":36.9827331,"lng":-84.0930963,"state":"KY","city":"Corbin","address":"88 Robert E Cox Road","zip":"40701","phone":"+1-606-404-4090","email":"","website":"https://www.billmorgantire.com/","hours":"Mo-Fr 08:00-18:00; Sa 09:00-12:00; Su off","brand":"","services":["tires"],"shopType":"tire_shop"},{"id":"shop-ky-lexington-bill-morgan-tire-company","name":"Bill Morgan Tire Company","slug":"ky-lexington-bill-morgan-tire-company","lat":38.0665458,"lng":-84.5515523,"state":"KY","city":"Lexington","address":"2245 Frankfort Court","zip":"40510","phone":"+1-859-255-4295","email":"","website":"https://billmorgantire.com/","hours":"Mo-Fr 08:00-18:00; Sa 09:00-12:00","brand":"","services":["tires"],"shopType":"tire_shop"},{"id":"shop-ky-owensboro-valvoline","name":"Valvoline","slug":"ky-owensboro-valvoline","lat":37.7395602,"lng":-87.1175904,"state":"KY","city":"Owensboro","address":"3425 Frederica Street","zip":"42301","phone":"","email":"","website":"https://store.vioc.com/ky/owensboro/oil-change-fg0018.html","hours":"","brand":"Valvoline","services":["oil_change"],"shopType":"quick_lube"},{"id":"shop-ky-richmond-valvoline","name":"Valvoline","slug":"ky-richmond-valvoline","lat":37.7323866,"lng":-84.2824213,"state":"KY","city":"Richmond","address":"849 Eastern Bypass","zip":"40475","phone":"+1-859-624-1696","email":"","website":"https://www.vioc.com/","hours":"Mo-Fr 7:30-19:30; Sa 7:30-18:00; Su 09:00-17:00","brand":"Valvoline","services":["oil_change"],"shopType":"quick_lube"},{"id":"shop-ky-salyersville-puckett-s-truck-stop","name":"Puckett's Truck Stop","slug":"ky-salyersville-puckett-s-truck-stop","lat":37.7326791,"lng":-83.0584603,"state":"KY","city":"Salyersville","address":"1512 Royalton Road","zip":"41465","phone":"+1 6063492508","email":"","website":"","hours":"Mo-Fr 08:00-18:00, Sa 08:00-15:00","brand":"","services":["tires"],"shopType":"general_repair"},{"id":"shop-ky-nicholasville-hrs-autocare-of-nicholasville","name":"HRS AutoCare Of Nicholasville","slug":"ky-nicholasville-hrs-autocare-of-nicholasville","lat":37.8979948,"lng":-84.5669361,"state":"KY","city":"Nicholasville","address":"105 Imperial Way","zip":"40356","phone":"+1 859-885-6448","email":"hrsauto.kh@gmail.com","website":"https://www.hrsautocare.com/","hours":"Mo-Fr 08:00-17:00","brand":"","services":["car_repair","oil_change","air_conditioning","transmission","brakes"],"shopType":"general_repair"},{"id":"shop-ky-louisville-christian-brothers-automotive-south-hurstbourne","name":"Christian Brothers Automotive - South Hurstbourne","slug":"ky-louisville-christian-brothers-automotive-south-hurstbourne","lat":38.1889499,"lng":-85.6060931,"state":"KY","city":"Louisville","address":"4400 South Hurstbourne Parkway","zip":"40299","phone":"+1-502-431-1656","email":"","website":"","hours":"Mo-Fr 07:00-18:00","brand":"Christian Brothers","services":["repair","car_repair","electrical","air_conditioning","oil_change","diagnostics","transmission","brakes","batteries","repairs","inspection","alignment"],"shopType":"general_repair"},{"id":"shop-ky-mount-washington-sawyers-towing","name":"Sawyers Towing","slug":"ky-mount-washington-sawyers-towing","lat":38.0528123,"lng":-85.5420824,"state":"KY","city":"Mount Washington","address":"432 Evans Lane","zip":"40047-7613","phone":"","email":"","website":"","hours":"","brand":"","services":["towing"],"shopType":"general_repair"},{"id":"shop-ky-campbellsville-the-body-mans-warehouse","name":"The Body Mans Warehouse","slug":"ky-campbellsville-the-body-mans-warehouse","lat":37.3231843,"lng":-85.357335,"state":"KY","city":"Campbellsville","address":"1030 New Columbia Road","zip":"42718","phone":"+1 270-572-7077","email":"","website":"https://thebodymanswarehouse.com/","hours":"","brand":"","services":["body_work"],"shopType":"body_shop"},{"id":"shop-ky-owensboro-mattingly-s-automotive-repair","name":"Mattingly's Automotive Repair","slug":"ky-owensboro-mattingly-s-automotive-repair","lat":37.7526383,"lng":-87.1017148,"state":"KY","city":"Owensboro","address":"2405 Veach Road","zip":"42303","phone":"+1 270 683 4251","email":"","website":"https://www.mattinglysautomotiverepair.com","hours":"Su off; Mo-Fr 08:00-17:00; Sa off","brand":"","services":["general_repair"],"shopType":"general_repair"},{"id":"shop-ky-ashland-onyx-tint-and-ceramics","name":"Onyx Tint and Ceramics","slug":"ky-ashland-onyx-tint-and-ceramics","lat":38.4807804,"lng":-82.6390324,"state":"KY","city":"Ashland","address":"1512 Front Street","zip":"41101-7849","phone":"+1-606-393-5548","email":"aaronsarantos@onyxtint.com","website":"https://onyxtint.com/","hours":"Mo-Fr 09:00-18:00; Sa 10:00-14:00","brand":"","services":["ceramic_coating","window_tinting","body_work","wrapping","paint_protection"],"shopType":"general_repair"},{"id":"shop-ky-pikeville-ken-s-towing-truck-service","name":"Ken's Towing & Truck Service","slug":"ky-pikeville-ken-s-towing-truck-service","lat":37.4904496,"lng":-82.5377805,"state":"KY","city":"Pikeville","address":"519 North Mayo Trail","zip":"41501","phone":"+1-606-432-3002","email":"ken@childerstruckparts.com","website":"https://www.kttsky.com/","hours":"","brand":"","services":["general_repair"],"shopType":"general_repair"},{"id":"shop-ky-water-valley-sumo-s-custom-repairs-llc","name":"Sumo’s Custom Repairs LLC","slug":"ky-water-valley-sumo-s-custom-repairs-llc","lat":36.5668038,"lng":-88.8095029,"state":"KY","city":"Water Valley","address":"16620 State Route 45 S","zip":"42085","phone":"+1-262-903-8303","email":"","website":"https://www.facebook.com/sumodru01","hours":"","brand":"","services":["general_repair"],"shopType":"general_repair"},{"id":"shop-ky-georgetown-kk-auto-detailing","name":"KK Auto Detailing","slug":"ky-georgetown-kk-auto-detailing","lat":38.2116441,"lng":-84.5547021,"state":"KY","city":"Georgetown","address":"341 East Washington Street","zip":"40324","phone":"+1-502-868-6133","email":"kkautodetailing@aol.com","website":"https://www.kkautodetailing.com","hours":"Mo-Fr 08:00-17:00; Sa-Su 09:00-12:00","brand":"","services":["detailing"],"shopType":"general_repair"},{"id":"shop-ky-lexington-valvoline","name":"Valvoline","slug":"ky-lexington-valvoline","lat":38.0155731,"lng":-84.4181988,"state":"KY","city":"Lexington","address":"1848 Plaudit Place","zip":"","phone":"","email":"","website":"https://store.vioc.com/ky/lexington/oil-change-040066.html","hours":"","brand":"Valvoline","services":["oil_change"],"shopType":"quick_lube"},{"id":"shop-ky-cold-spring-caliber-collision","name":"Caliber Collision","slug":"ky-cold-spring-caliber-collision","lat":39.0162901,"lng":-84.433663,"state":"KY","city":"Cold Spring","address":"4411 Alexandria Pike","zip":"41076","phone":"+1-859-781-5800","email":"","website":"https://www.caliber.com/find-a-location/cold-spring","hours":"Mo-Fr 07:30-17:30","brand":"Caliber Collision","services":["body_work","body_repair"],"shopType":"body_shop"},{"id":"shop-ky-cold-spring-moore-s-garage-auto-repair","name":"Moore's Garage Auto Repair","slug":"ky-cold-spring-moore-s-garage-auto-repair","lat":39.0096037,"lng":-84.4639355,"state":"KY","city":"Cold Spring","address":"5671 AA Highway","zip":"41076","phone":"+1-859-781-6060","email":"","website":"https://mooresautomart.com","hours":"","brand":"","services":["general_repair"],"shopType":"general_repair"},{"id":"shop-ky-covington-kerry-collision-center","name":"Kerry Collision Center","slug":"ky-covington-kerry-collision-center","lat":39.0863814,"lng":-84.5096499,"state":"KY","city":"Covington","address":"24 East 5th Street","zip":"41011","phone":"","email":"","website":"","hours":"","brand":"","services":["collision_repair","body_work"],"shopType":"body_shop"},{"id":"shop-ky-dayton-boruske-brothers-collision-center","name":"Boruske Brothers Collision Center","slug":"ky-dayton-boruske-brothers-collision-center","lat":39.1119642,"lng":-84.475685,"state":"KY","city":"Dayton","address":"407 6th Avenue","zip":"41074","phone":"","email":"","website":"","hours":"","brand":"","services":["body_work"],"shopType":"body_shop"},{"id":"shop-ky-burlington-steele-s-hometown-tire","name":"Steele’s Hometown Tire","slug":"ky-burlington-steele-s-hometown-tire","lat":39.026635,"lng":-84.7253874,"state":"KY","city":"Burlington","address":"3026 Torrid Street","zip":"41005","phone":"","email":"","website":"https://www.steeleshometowntire.com/","hours":"","brand":"","services":["tires"],"shopType":"tire_shop"},{"id":"shop-ky-bellevue-konen-s-pittstop","name":"Konen's Pittstop","slug":"ky-bellevue-konen-s-pittstop","lat":39.0990452,"lng":-84.4796075,"state":"KY","city":"Bellevue","address":"539 Berry Avenue","zip":"41073","phone":"+1-859-888-1990","email":"","website":"https://konenspittstop.com/","hours":"Mo-Fr 08:00-18:00","brand":"","services":["general_repair"],"shopType":"general_repair"},{"id":"shop-ky-burlington-valvoline","name":"Valvoline","slug":"ky-burlington-valvoline","lat":39.019846,"lng":-84.6893147,"state":"KY","city":"Burlington","address":"1736 Wildcat Boulevard","zip":"41005","phone":"","email":"","website":"","hours":"","brand":"Valvoline","services":["oil_change"],"shopType":"quick_lube"},{"id":"shop-ky-erlanger-aamco","name":"AAMCO","slug":"ky-erlanger-aamco","lat":39.0194846,"lng":-84.5954346,"state":"KY","city":"Erlanger","address":"3210 Dixie Highway","zip":"41018","phone":"+1-859-657-8197","email":"","website":"","hours":"Mo-Fr 8:00-17:00; Sa-Su off","brand":"AAMCO","services":["transmission"],"shopType":"transmission_shop"},{"id":"shop-ky-lexington-perfect-auto-care","name":"Perfect Auto Care","slug":"ky-lexington-perfect-auto-care","lat":38.0413234,"lng":-84.494209,"state":"KY","city":"Lexington","address":"305 East High Street","zip":"40507","phone":"","email":"","website":"","hours":"","brand":"","services":["general_repair"],"shopType":"general_repair"},{"id":"shop-ky-sonora-dennie-s-truck-trailer-repair","name":"Dennie's Truck & Trailer Repair","slug":"ky-sonora-dennie-s-truck-trailer-repair","lat":37.5224015,"lng":-85.8826094,"state":"KY","city":"Sonora","address":"450 East Western Avenue","zip":"42776","phone":"+1 270-737-5024","email":"","website":"https://www.denniestruckandtrailerrepair.net/","hours":"Mo-Fr 08:00-18:00","brand":"","services":["general_repair"],"shopType":"general_repair"},{"id":"shop-ky-lexington-tire-discounters","name":"Tire Discounters","slug":"ky-lexington-tire-discounters","lat":38.0168219,"lng":-84.4103364,"state":"KY","city":"Lexington","address":"2080 Bryant Road","zip":"","phone":"","email":"","website":"","hours":"","brand":"Tire Discounters","services":["tires"],"shopType":"tire_shop"},{"id":"shop-ky-lexington-goodyear-tires","name":"Goodyear Tires","slug":"ky-lexington-goodyear-tires","lat":38.017212,"lng":-84.5266807,"state":"KY","city":"Lexington","address":"396 Southland Drive","zip":"","phone":"","email":"","website":"https://www.goodyear.com/","hours":"Mo-Sa 07:00-18:00; Su off","brand":"Goodyear","services":["tires"],"shopType":"tire_shop"},{"id":"shop-ky-louisville-tire-discounters","name":"Tire Discounters","slug":"ky-louisville-tire-discounters","lat":38.2943032,"lng":-85.5565112,"state":"KY","city":"Louisville","address":"10530 Westport Road","zip":"40241","phone":"","email":"","website":"","hours":"","brand":"Tire Discounters","services":["tires"],"shopType":"tire_shop"},{"id":"shop-ky-louisville-carteck","name":"Carteck","slug":"ky-louisville-carteck","lat":38.2339951,"lng":-85.7195184,"state":"KY","city":"Louisville","address":"Baxter Avenue","zip":"","phone":"","email":"","website":"","hours":"","brand":"","services":["general_repair"],"shopType":"general_repair"},{"id":"shop-ky-louisville-valvoline","name":"Valvoline","slug":"ky-louisville-valvoline","lat":38.2320478,"lng":-85.7098299,"state":"KY","city":"Louisville","address":"1450 Bardstown Road","zip":"40204","phone":"+15024583315","email":"","website":"https://store.vioc.com/ky/louisville/oil-change-040014.html","hours":"","brand":"Valvoline","services":["tires","oil_change","tyres"],"shopType":"quick_lube"},{"id":"shop-ky-louisville-tredroc-tire-services","name":"Tredroc Tire Services","slug":"ky-louisville-tredroc-tire-services","lat":38.1792422,"lng":-85.7568945,"state":"KY","city":"Louisville","address":"4703 Allmond Avenue","zip":"40209","phone":"+1-502-554-9352","email":"cbates@tredroc.com","website":"https://Tredroc.com","hours":"Mo-Fr 07:00-17:00","brand":"","services":["tires"],"shopType":"tire_shop"},{"id":"shop-ky-st-matthews-neil-huffman-nissan-collision-center","name":"Neil Huffman Nissan - Collision Center","slug":"ky-st-matthews-neil-huffman-nissan-collision-center","lat":38.2514784,"lng":-85.6439828,"state":"KY","city":"St Matthews","address":"4126 Shelbyville Road","zip":"40207","phone":"","email":"","website":"","hours":"","brand":"","services":["body_work"],"shopType":"body_shop"},{"id":"shop-ky-louisville-valvoline-2","name":"Valvoline","slug":"ky-louisville-valvoline-2","lat":38.2902446,"lng":-85.5102528,"state":"KY","city":"Louisville","address":"12416 La Grange Road","zip":"40245","phone":"","email":"","website":"https://store.vioc.com/ky/louisville/oil-change-040106.html","hours":"","brand":"Valvoline","services":["oil_change"],"shopType":"quick_lube"},{"id":"shop-ky-louisville-grainline-tires","name":"Grainline Tires","slug":"ky-louisville-grainline-tires","lat":38.148252,"lng":-85.7359921,"state":"KY","city":"Louisville","address":"7011 Grade Lane","zip":"40213","phone":"","email":"","website":"","hours":"","brand":"","services":["tires"],"shopType":"tire_shop"},{"id":"shop-ky-louisville-carter-and-anderson-auto-sales","name":"Carter and Anderson Auto Sales","slug":"ky-louisville-carter-and-anderson-auto-sales","lat":38.2357709,"lng":-85.7281506,"state":"KY","city":"Louisville","address":"1020 Barret Avenue","zip":"40204","phone":"","email":"","website":"","hours":"","brand":"","services":["general_repair"],"shopType":"general_repair"},{"id":"shop-ky-louisville-reece-service-center","name":"Reece Service Center","slug":"ky-louisville-reece-service-center","lat":38.2253733,"lng":-85.7073689,"state":"KY","city":"Louisville","address":"1632 Norris Place","zip":"40205","phone":"+1-502-458-9104","email":"","website":"https://reeceserviceinc.godaddysites.com","hours":"Mo-Fr 07:30-17:30","brand":"","services":["general_repair"],"shopType":"general_repair"},{"id":"shop-ky-louisville-michel-tires-plus","name":"Michel Tires Plus","slug":"ky-louisville-michel-tires-plus","lat":38.253676,"lng":-85.7446876,"state":"KY","city":"Louisville","address":"434 East Market Street","zip":"40202","phone":"+1 502 907 2921","email":"","website":"https://local.tiresplus.com/kentucky/louisville/434-e-market-st/","hours":"Mo-Sa 07:00-18:00","brand":"","services":["tires"],"shopType":"tire_shop"},{"id":"shop-ky-louisville-ken-towery-s-tire-and-auto-care","name":"Ken Towery's Tire and Auto Care","slug":"ky-louisville-ken-towery-s-tire-and-auto-care","lat":38.2988629,"lng":-85.5406947,"state":"KY","city":"Louisville","address":"11300 Westport Road","zip":"40241","phone":"","email":"","website":"","hours":"","brand":"","services":["tires"],"shopType":"tire_shop"},{"id":"shop-ky-louisville-harrod-s-creek-auto-service","name":"Harrod's Creek Auto Service","slug":"ky-louisville-harrod-s-creek-auto-service","lat":38.3270326,"lng":-85.6329097,"state":"KY","city":"Louisville","address":"6337 River Road","zip":"40059","phone":"","email":"","website":"","hours":"","brand":"","services":["general_repair"],"shopType":"general_repair"},{"id":"shop-ky-louisville-art-s-service-center","name":"Art's Service Center","slug":"ky-louisville-art-s-service-center","lat":38.1985926,"lng":-85.7074999,"state":"KY","city":"Louisville","address":"4213 Poplar Level Road","zip":"40213","phone":"","email":"","website":"","hours":"","brand":"","services":["general_repair"],"shopType":"general_repair"},{"id":"shop-ky-st-matthews-meineke","name":"Meineke","slug":"ky-st-matthews-meineke","lat":38.2530108,"lng":-85.652822,"state":"KY","city":"St Matthews","address":"3949 Shelbyville Road","zip":"40207","phone":"","email":"","website":"","hours":"","brand":"Meineke","services":["exhaust"],"shopType":"general_repair"},{"id":"shop-ky-louisville-valvoline-3","name":"Valvoline","slug":"ky-louisville-valvoline-3","lat":38.2525924,"lng":-85.6574581,"state":"KY","city":"Louisville","address":"3800 Lexington Road","zip":"40207","phone":"","email":"","website":"https://store.vioc.com/ky/stmatthews/oil-change-040133.html","hours":"","brand":"Valvoline","services":["oil_change"],"shopType":"quick_lube"},{"id":"shop-ky-louisville-pruitt-s-automotive","name":"Pruitt's Automotive","slug":"ky-louisville-pruitt-s-automotive","lat":38.2528629,"lng":-85.6582849,"state":"KY","city":"Louisville","address":"3795 Lexington Road","zip":"40207","phone":"+1-502-896-9224","email":"","website":"","hours":"","brand":"","services":["general_repair"],"shopType":"general_repair"},{"id":"shop-ky-louisville-heustis-service-center","name":"Heustis Service Center","slug":"ky-louisville-heustis-service-center","lat":38.2539125,"lng":-85.671341,"state":"KY","city":"Louisville","address":"3330 Frankfort Avenue","zip":"40206","phone":"+1-502-895-8107","email":"","website":"","hours":"","brand":"","services":["general_repair"],"shopType":"general_repair"},{"id":"shop-ky-louisville-raben-tire-and-auto-service-louisville","name":"Raben Tire and Auto Service - Louisville","slug":"ky-louisville-raben-tire-and-auto-service-louisville","lat":38.1918014,"lng":-85.7520985,"state":"KY","city":"Louisville","address":"4334 Crittenden Drive","zip":"40209","phone":"","email":"","website":"","hours":"","brand":"","services":["tires"],"shopType":"tire_shop"},{"id":"shop-ky-plantation-valvoline","name":"Valvoline","slug":"ky-plantation-valvoline","lat":38.2808674,"lng":-85.5920479,"state":"KY","city":"Plantation","address":"8701 Westport Road","zip":"40242","phone":"","email":"","website":"https://store.vioc.com/ky/plantation/oil-change-040012.html","hours":"Mo-Fr 08:00-19:00; Sa 08:00-18:00; Su 11:00-17:00","brand":"Valvoline","services":["oil_change"],"shopType":"quick_lube"},{"id":"shop-ky-plantation-brakeway","name":"Brakeway","slug":"ky-plantation-brakeway","lat":38.2809635,"lng":-85.5903011,"state":"KY","city":"Plantation","address":"8715 Westport Road","zip":"40242","phone":"","email":"","website":"","hours":"","brand":"","services":["brakes"],"shopType":"general_repair"},{"id":"shop-ky-louisville-ballard-s-alignment-services","name":"Ballard's Alignment Services","slug":"ky-louisville-ballard-s-alignment-services","lat":38.2014306,"lng":-85.7639875,"state":"KY","city":"Louisville","address":"3201 South 3rd Street","zip":"40214","phone":"+1-502-366-1144","email":"","website":"","hours":"","brand":"","services":["alignment"],"shopType":"general_repair"},{"id":"shop-ky-rolling-hills-strickland-brothers-10-minute-oil-change","name":"Strickland Brothers 10 Minute Oil Change","slug":"ky-rolling-hills-strickland-brothers-10-minute-oil-change","lat":38.2856233,"lng":-85.5780175,"state":"KY","city":"Rolling Hills","address":"9260 Westport Road","zip":"40242","phone":"","email":"","website":"","hours":"","brand":"","services":["oil_change"],"shopType":"quick_lube"},{"id":"shop-ky-st-matthews-jiffy-lube","name":"Jiffy Lube","slug":"ky-st-matthews-jiffy-lube","lat":38.2592679,"lng":-85.6417168,"state":"KY","city":"St Matthews","address":"4180 Westport Road","zip":"40207","phone":"+1-502-896-2905","email":"","website":"","hours":"","brand":"Jiffy Lube","services":["oil_change"],"shopType":"quick_lube"},{"id":"shop-ky-st-matthews-medley-s-auto-care","name":"Medley's Auto Care","slug":"ky-st-matthews-medley-s-auto-care","lat":38.2510085,"lng":-85.6278762,"state":"KY","city":"St Matthews","address":"4601 Shelbyville Road","zip":"40207","phone":"","email":"","website":"","hours":"","brand":"","services":["general_repair"],"shopType":"general_repair"},{"id":"shop-ky-st-matthews-tire-discounters","name":"Tire Discounters","slug":"ky-st-matthews-tire-discounters","lat":38.2509879,"lng":-85.6253648,"state":"KY","city":"St Matthews","address":"4909 Shelbyville Road","zip":"40207","phone":"","email":"","website":"","hours":"","brand":"Tire Discounters","services":["tires"],"shopType":"tire_shop"},{"id":"shop-ky-st-matthews-valvoline","name":"Valvoline","slug":"ky-st-matthews-valvoline","lat":38.2519003,"lng":-85.6381615,"state":"KY","city":"St Matthews","address":"4213 Shelbyville Road","zip":"40207","phone":"","email":"","website":"https://store.vioc.com/ky/louisville/oil-change-040016.html","hours":"","brand":"Valvoline","services":["oil_change"],"shopType":"quick_lube"},{"id":"shop-ky-louisville-big-o-tires","name":"Big O Tires","slug":"ky-louisville-big-o-tires","lat":38.0724266,"lng":-85.8851781,"state":"KY","city":"Louisville","address":"12614 Dixie Highway","zip":"40272","phone":"","email":"","website":"","hours":"","brand":"Big O Tires","services":["tires"],"shopType":"tire_shop"},{"id":"shop-ky-louisville-valvoline-4","name":"Valvoline","slug":"ky-louisville-valvoline-4","lat":38.2196856,"lng":-85.6287024,"state":"KY","city":"Louisville","address":"3920 Taylorsville Road","zip":"40220","phone":"","email":"","website":"https://store.vioc.com/ky/louisville/oil-change-040130.html","hours":"","brand":"Valvoline","services":["oil_change"],"shopType":"quick_lube"},{"id":"shop-ky-louisville-fern-creek-truck-and-auto","name":"Fern Creek Truck and Auto","slug":"ky-louisville-fern-creek-truck-and-auto","lat":38.1627972,"lng":-85.5965767,"state":"KY","city":"Louisville","address":"5702 Bardstown Road","zip":"40291","phone":"","email":"","website":"","hours":"","brand":"","services":["general_repair"],"shopType":"general_repair"},{"id":"shop-ky-louisville-valvoline-5","name":"Valvoline","slug":"ky-louisville-valvoline-5","lat":38.0919083,"lng":-85.6695596,"state":"KY","city":"Louisville","address":"11810 Antonia Way","zip":"40229","phone":"","email":"","website":"","hours":"","brand":"Valvoline","services":["oil_change"],"shopType":"quick_lube"},{"id":"shop-ky-louisville-valvoline-6","name":"Valvoline","slug":"ky-louisville-valvoline-6","lat":38.1452649,"lng":-85.7755451,"state":"KY","city":"Louisville","address":"7401 3Rd Street Road","zip":"40214","phone":"","email":"","website":"https://store.vioc.com/ky/louisville/oil-change-040008.html","hours":"","brand":"Valvoline","services":["oil_change"],"shopType":"quick_lube"},{"id":"shop-ky-lexingtion-jiffy-lube","name":"Jiffy Lube","slug":"ky-lexingtion-jiffy-lube","lat":38.0290222,"lng":-84.5381395,"state":"KY","city":"Lexingtion","address":"801 Lane Allen Road","zip":"40504","phone":"","email":"","website":"","hours":"Mo-Fr 8:00-18:00; Sa 8:00-17:00; Su 11:00-16:00","brand":"Jiffy Lube","services":["oil_change"],"shopType":"quick_lube"},{"id":"shop-ky-richmond-roberto-s-auto-repair","name":"Roberto's Auto Repair","slug":"ky-richmond-roberto-s-auto-repair","lat":37.7464775,"lng":-84.283983,"state":"KY","city":"Richmond","address":"221 North Estill Avenue","zip":"40475","phone":"+1-859-624-0038","email":"","website":"https://robertosautorepair.wordpress.com","hours":"Mo-Fr 08:00-17:00","brand":"","services":["general_repair"],"shopType":"general_repair"},{"id":"shop-ky-lexington-ken-towery-s-tire-and-autocare","name":"Ken Towery's Tire and AutoCare","slug":"ky-lexington-ken-towery-s-tire-and-autocare","lat":38.0596357,"lng":-84.4650874,"state":"KY","city":"Lexington","address":"304 East New Circle Road","zip":"","phone":"","email":"","website":"","hours":"","brand":"","services":["tires"],"shopType":"tire_shop"},{"id":"shop-ky-lexington-valvoline-instant-oil-change-2","name":"Valvoline Instant Oil Change","slug":"ky-lexington-valvoline-instant-oil-change-2","lat":38.0087435,"lng":-84.5171522,"state":"KY","city":"Lexington","address":"2172;3792 Nicholasville Road;Palomar Centre Drive","zip":"","phone":"","email":"","website":"https://store.vioc.com/ky/lexington/oil-change-040027.html","hours":"","brand":"Valvoline","services":["oil_change"],"shopType":"quick_lube"},{"id":"shop-ky-lexington-exhaust-pro","name":"Exhaust Pro","slug":"ky-lexington-exhaust-pro","lat":37.9812018,"lng":-84.5501037,"state":"KY","city":"Lexington","address":"3620 Boston Road","zip":"40514","phone":"+18592239866","email":"","website":"","hours":"Mo-Fr 0730-1730, Sa 0730-1400","brand":"","services":["exhaust"],"shopType":"general_repair"},{"id":"shop-ky-lexington-ken-towery-tire-store","name":"Ken Towery Tire Store","slug":"ky-lexington-ken-towery-tire-store","lat":37.9809994,"lng":-84.5502308,"state":"KY","city":"Lexington","address":"3630 Boston Road","zip":"","phone":"","email":"","website":"","hours":"","brand":"","services":["tires"],"shopType":"tire_shop"},{"id":"shop-ky-lexington-brakes-4-less","name":"Brakes 4 Less","slug":"ky-lexington-brakes-4-less","lat":38.0676035,"lng":-84.4721513,"state":"KY","city":"Lexington","address":"177 West New Circle Road","zip":"40505","phone":"+1 859-766-7867","email":"","website":"","hours":"Mo-Sa 08:00-17:00","brand":"","services":["brakes"],"shopType":"general_repair"},{"id":"shop-ky-lexington-quantrell-collision","name":"Quantrell Collision","slug":"ky-lexington-quantrell-collision","lat":38.0316665,"lng":-84.4566404,"state":"KY","city":"Lexington","address":"1869 Liberty Road","zip":"40505-4207","phone":"","email":"","website":"https://www.quantrellcollision.com/","hours":"","brand":"","services":["body_work","body_repair"],"shopType":"body_shop"},{"id":"shop-ky-lexington-valvoline-2","name":"Valvoline","slug":"ky-lexington-valvoline-2","lat":38.0061426,"lng":-84.4515564,"state":"KY","city":"Lexington","address":"2940 Richmond Road","zip":"","phone":"","email":"","website":"https://store.vioc.com/ky/lexington/oil-change-040023.html","hours":"","brand":"Valvoline","services":["oil_change"],"shopType":"quick_lube"},{"id":"shop-ky-lexington-midas","name":"Midas","slug":"ky-lexington-midas","lat":37.9681348,"lng":-84.5005439,"state":"KY","city":"Lexington","address":"4210 Saron Drive","zip":"","phone":"","email":"","website":"","hours":"","brand":"Midas","services":["general_repair"],"shopType":"general_repair"},{"id":"shop-ky-georgetown-tire-discounter-s","name":"Tire Discounter's","slug":"ky-georgetown-tire-discounter-s","lat":38.2336631,"lng":-84.5364441,"state":"KY","city":"Georgetown","address":"113 Lawson Drive","zip":"40324","phone":"","email":"","website":"","hours":"","brand":"","services":["tires"],"shopType":"tire_shop"},{"id":"shop-ky-unknown-27-auto-services-repair","name":"27 Auto Services & Repair","slug":"ky-unknown-27-auto-services-repair","lat":38.7922658,"lng":-84.3528893,"state":"KY","city":"","address":"10223 Highway 27 North","zip":"41006","phone":"","email":"","website":"","hours":"","brand":"","services":["general_repair"],"shopType":"general_repair"},{"id":"shop-ky-hebron-tire-discounters","name":"Tire Discounters","slug":"ky-hebron-tire-discounters","lat":39.0658137,"lng":-84.7051085,"state":"KY","city":"Hebron","address":"2065 Petersburg Road","zip":"41048","phone":"+1-859-538-1587","email":"","website":"","hours":"Mo-Fr 08:00-19:00,Sa 08:00-14:00","brand":"Tire Discounters","services":["tires"],"shopType":"tire_shop"},{"id":"shop-ky-paducah-purcell-tire-and-service-center","name":"Purcell Tire and Service Center","slug":"ky-paducah-purcell-tire-and-service-center","lat":37.075278,"lng":-88.6929359,"state":"KY","city":"Paducah","address":"5165 Hinkleville Road","zip":"42001","phone":"","email":"","website":"","hours":"","brand":"","services":["tires"],"shopType":"tire_shop"},{"id":"shop-ky-louisville-tire-discounter","name":"Tire Discounter","slug":"ky-louisville-tire-discounter","lat":38.311353,"lng":-85.5731435,"state":"KY","city":"Louisville","address":"9710 Von Allmen Court","zip":"40241","phone":"","email":"","website":"","hours":"","brand":"","services":["tires"],"shopType":"tire_shop"},{"id":"shop-ky-paducah-plaza-tire-service","name":"Plaza Tire Service","slug":"ky-paducah-plaza-tire-service","lat":37.0753662,"lng":-88.6926153,"state":"KY","city":"Paducah","address":"5155 Hinkleville Road","zip":"42001","phone":"","email":"","website":"","hours":"","brand":"","services":["tires"],"shopType":"tire_shop"},{"id":"shop-ky-falmouth-s-s-auto-repair","name":"S & S Auto Repair","slug":"ky-falmouth-s-s-auto-repair","lat":38.6782558,"lng":-84.3298072,"state":"KY","city":"Falmouth","address":"106 2nd Street","zip":"41040","phone":"","email":"","website":"","hours":"","brand":"","services":["general_repair"],"shopType":"general_repair"},{"id":"shop-ky-falmouth-perkins-tire-auto-repair","name":"Perkins Tire & Auto Repair","slug":"ky-falmouth-perkins-tire-auto-repair","lat":38.6761092,"lng":-84.3402752,"state":"KY","city":"Falmouth","address":"914 Ridgeway Avenue","zip":"41040","phone":"+1-859-951-1096","email":"","website":"","hours":"","brand":"","services":["tires"],"shopType":"tire_shop"},{"id":"shop-ky-stanton-joey-s-muffler-shop","name":"Joey's Muffler Shop","slug":"ky-stanton-joey-s-muffler-shop","lat":37.8456687,"lng":-83.8627915,"state":"KY","city":"Stanton","address":"231 West College Avenue","zip":"40380","phone":"","email":"","website":"","hours":"Tu-Fr 09:00-17:00, Sa 07:00-14:00","brand":"","services":["muffler","exhaust"],"shopType":"general_repair"},{"id":"shop-ky-unknown-integrity-auto","name":"Integrity Auto","slug":"ky-unknown-integrity-auto","lat":38.7752634,"lng":-84.3519852,"state":"KY","city":"","address":"9003 Highway 27 North","zip":"41006","phone":"+1-859-640-2039","email":"","website":"","hours":"","brand":"","services":["general_repair"],"shopType":"general_repair"},{"id":"shop-ky-owensboro-hollywood-window-film-auto-accessories","name":"Hollywood Window Film & Auto Accessories","slug":"ky-owensboro-hollywood-window-film-auto-accessories","lat":37.749843,"lng":-87.112608,"state":"KY","city":"Owensboro","address":"2616 Frederica Street","zip":"42301","phone":"+1-270-926-3503","email":"","website":"","hours":"","brand":"","services":["general_repair"],"shopType":"general_repair"},{"id":"shop-ky-morehead-s-h-caudill-s-auto-repair","name":"S & H Caudill's Auto Repair","slug":"ky-morehead-s-h-caudill-s-auto-repair","lat":38.2374329,"lng":-83.5071224,"state":"KY","city":"Morehead","address":"5835 Flemingsburg Road","zip":"40351","phone":"+1-606-548-9070","email":"","website":"https://shcaudillsauto.com","hours":"Mo-Fr 07:00-17:00, Sa 08:00-14:00","brand":"","services":["general_repair"],"shopType":"general_repair"},{"id":"shop-ky-radcliff-take-5-car-wash","name":"Take 5 Car Wash","slug":"ky-radcliff-take-5-car-wash","lat":37.7912231,"lng":-85.9121586,"state":"KY","city":"Radcliff","address":"4060 Dixie Highway South","zip":"40160","phone":"+1-270-600-0620","email":"","website":"https://www.take5carwash.com/","hours":"","brand":"Take 5","services":["general_repair"],"shopType":"general_repair"},{"id":"shop-ky-radcliff-michel-tires-plus","name":"Michel Tires Plus","slug":"ky-radcliff-michel-tires-plus","lat":37.8614657,"lng":-85.9519518,"state":"KY","city":"Radcliff","address":"669 Knox Boulevard","zip":"40160","phone":"+1-270-506-0522","email":"","website":"https://local.tiresplus.com","hours":"","brand":"","services":["tires"],"shopType":"tire_shop"},{"id":"shop-ky-radcliff-joy-automotive","name":"Joy Automotive","slug":"ky-radcliff-joy-automotive","lat":37.8577151,"lng":-85.9534852,"state":"KY","city":"Radcliff","address":"1510 North Dixie Boulevard","zip":"40160","phone":"+1-270-319-4671","email":"","website":"https://choosejoyautomotive.com/","hours":"","brand":"","services":["general_repair"],"shopType":"general_repair"},{"id":"shop-ky-elizabethtown-take-5-car-wash","name":"Take 5 Car Wash","slug":"ky-elizabethtown-take-5-car-wash","lat":37.740572,"lng":-85.8894475,"state":"KY","city":"Elizabethtown","address":"2009 North Dixie Highway","zip":"42701","phone":"+1-270-951-0927","email":"","website":"https://www.take5carwashes.com/locations/kentucky/elizabethtown/408/","hours":"Mo-Fr 08:00-19:00; Sa-Su 08:00-19:00","brand":"Take 5","services":["general_repair"],"shopType":"general_repair"},{"id":"shop-ky-elizabethtown-payless-muffler-and-brakes","name":"Payless Muffler and Brakes","slug":"ky-elizabethtown-payless-muffler-and-brakes","lat":37.7417051,"lng":-85.8913429,"state":"KY","city":"Elizabethtown","address":"2108 North Dixie Highway","zip":"42701","phone":"+1-270-769-6898","email":"","website":"","hours":"","brand":"","services":["exhaust","brakes"],"shopType":"general_repair"},{"id":"shop-ky-radcliff-drive-rite-automotive","name":"Drive Rite Automotive","slug":"ky-radcliff-drive-rite-automotive","lat":37.8491456,"lng":-85.9462401,"state":"KY","city":"Radcliff","address":"916 North Dixie Boulevard","zip":"40160","phone":"+1-270-390-4128","email":"","website":"","hours":"","brand":"","services":["general_repair"],"shopType":"general_repair"},{"id":"shop-ky-radcliff-good-ole-boys-auto-care","name":"Good Ole Boys Auto Care","slug":"ky-radcliff-good-ole-boys-auto-care","lat":37.8503772,"lng":-85.9490043,"state":"KY","city":"Radcliff","address":"1047 Dixie Highway North","zip":"40160","phone":"+1-270-352-5515","email":"","website":"","hours":"","brand":"","services":["general_repair"],"shopType":"general_repair"},{"id":"shop-ky-radcliff-payless-muffler-brakes","name":"Payless Muffler & Brakes","slug":"ky-radcliff-payless-muffler-brakes","lat":37.8505134,"lng":-85.9485657,"state":"KY","city":"Radcliff","address":"1047 Dixie Highway North","zip":"40160","phone":"+1-270-769-6898","email":"cdugger65@gmail.com","website":"https://www.paylessmufflerandbrakesky.com/","hours":"","brand":"","services":["exhaust","brakes"],"shopType":"general_repair"},{"id":"shop-ky-radcliff-big-o-tires","name":"Big O Tires","slug":"ky-radcliff-big-o-tires","lat":37.856188,"lng":-85.9523808,"state":"KY","city":"Radcliff","address":"1470 Dixie Highway North","zip":"40160","phone":"+1-270-495-0599","email":"","website":"https://www.bigotires.com/","hours":"","brand":"Big O Tires","services":["tires"],"shopType":"tire_shop"},{"id":"shop-ky-crestwood-certified-express-lube-auto-service","name":"Certified Express Lube & Auto Service","slug":"ky-crestwood-certified-express-lube-auto-service","lat":38.3222298,"lng":-85.4715396,"state":"KY","city":"Crestwood","address":"6540 KY-146","zip":"40014","phone":"+15022417166","email":"","website":"https://www.certifiedcarpros.com/","hours":"","brand":"","services":["oil_change"],"shopType":"quick_lube"},{"id":"shop-ky-radcliff-hard-road-automotive","name":"Hard Road Automotive","slug":"ky-radcliff-hard-road-automotive","lat":37.8363984,"lng":-85.9373307,"state":"KY","city":"Radcliff","address":"343 South Wilson Road","zip":"40160","phone":"+1-270-801-0363","email":"","website":"","hours":"","brand":"","services":["general_repair"],"shopType":"general_repair"},{"id":"shop-ky-radcliff-massie-automotive","name":"Massie Automotive","slug":"ky-radcliff-massie-automotive","lat":37.8326036,"lng":-85.9349009,"state":"KY","city":"Radcliff","address":"644 South Wilson Road","zip":"40160","phone":"+1-270-351-6516","email":"","website":"","hours":"","brand":"","services":["general_repair"],"shopType":"general_repair"},{"id":"shop-ky-radcliff-finny-s-complete-auto-repair","name":"Finny's Complete Auto Repair","slug":"ky-radcliff-finny-s-complete-auto-repair","lat":37.8443743,"lng":-85.941959,"state":"KY","city":"Radcliff","address":"466 Dixie Highway North","zip":"40160","phone":"+1-270-351-5515","email":"","website":"www.facebook.com/Finnysauto","hours":"Mo-Fr 09:00-18:00; Sa 09:00-17:00; Su off","brand":"","services":["car_repair"],"shopType":"general_repair"},{"id":"shop-ky-radcliff-meineke","name":"Meineke","slug":"ky-radcliff-meineke","lat":37.8099625,"lng":-85.9222515,"state":"KY","city":"Radcliff","address":"2197 South Dixie Boulevard","zip":"40160","phone":"+1-270-936-8000","email":"","website":"https://www.meineke.com/locations/ky/radcliff-2171/","hours":"Mo-Fr 07:30-18:00; Sa 07:30-17:00; Su off","brand":"Meineke","services":["exhaust"],"shopType":"general_repair"},{"id":"shop-ky-radcliff-gold-city-towing","name":"Gold City Towing","slug":"ky-radcliff-gold-city-towing","lat":37.816295,"lng":-85.9235142,"state":"KY","city":"Radcliff","address":"1922 South Dixie Boulevard","zip":"40160","phone":"+1-270-351-5993","email":"goldcitytowing@hotmail.com","website":"https://www.goldcitytowing.com/","hours":"Mo-Fr 08:00-17:00; Sa 08:00-12:00; Su off","brand":"","services":["towing"],"shopType":"general_repair"},{"id":"shop-ky-radcliff-jack-hart-body-shop","name":"Jack Hart Body Shop","slug":"ky-radcliff-jack-hart-body-shop","lat":37.8225681,"lng":-85.9258952,"state":"KY","city":"Radcliff","address":"1468 South Dixie Boulevard","zip":"40160","phone":"+1-270-351-3637","email":"","website":"https://www.jackhartbodyshop.com/","hours":"","brand":"","services":["painting","body_work","body_repair"],"shopType":"body_shop"},{"id":"shop-ky-owensboro-east-side-automotive","name":"East Side Automotive","slug":"ky-owensboro-east-side-automotive","lat":37.7823709,"lng":-87.0774415,"state":"KY","city":"Owensboro","address":"2920 East 4th Street","zip":"42303","phone":"+12704781084","email":"eastsideautomotive2920@gmail.com","website":"https://www.bandlautosalesky.com/","hours":"Mo-Fr 08:00-17:00","brand":"","services":["general_repair"],"shopType":"general_repair"},{"id":"shop-ky-taylorsville-taylorsville-auto-center","name":"Taylorsville Auto Center","slug":"ky-taylorsville-taylorsville-auto-center","lat":38.0941094,"lng":-85.3617131,"state":"KY","city":"Taylorsville","address":"77 Elk Creek Park Drive","zip":"40071","phone":"+15023540477","email":"","website":"","hours":"Mo-Fr 08:00-17:00","brand":"","services":["general_repair"],"shopType":"general_repair"},{"id":"shop-ky-princeton-purcell-tire-and-service-center","name":"Purcell Tire and Service Center","slug":"ky-princeton-purcell-tire-and-service-center","lat":37.1128463,"lng":-87.9005322,"state":"KY","city":"Princeton","address":"309 US Hwy 62 W","zip":"42445","phone":"+1-270-365-7291","email":"","website":"https://www.purcelltire.com/stores/view/princeton-kentucky/","hours":"","brand":"","services":["tires"],"shopType":"tire_shop"},{"id":"shop-ky-princeton-hallum-sons-automotive-napa-auto-care","name":"Hallum & Sons Automotive - NAPA Auto Care","slug":"ky-princeton-hallum-sons-automotive-napa-auto-care","lat":37.0971892,"lng":-87.8824383,"state":"KY","city":"Princeton","address":"614 Cadiz Street","zip":"42445","phone":"+1-270-365-1777","email":"","website":"https://www.facebook.com/profile.php?id=100070799063623","hours":"Mon-Fri 8 AM - 5 PM. Closed Sat-Sun","brand":"","services":["general_repair"],"shopType":"general_repair"},{"id":"shop-ky-princeton-markham-automotive","name":"Markham Automotive","slug":"ky-princeton-markham-automotive","lat":37.1229658,"lng":-87.8959843,"state":"KY","city":"Princeton","address":"255 Northfield Drive","zip":"42445","phone":"+1-270-365-0070","email":"markhamautomotive@yahoo.com","website":"https://www.facebook.com/profile.php?id=100063509563006","hours":"Mo-Fr 06:00-11:00,12:00-15:00; Sa,Su off","brand":"","services":["general_repair"],"shopType":"general_repair"},{"id":"shop-ky-elizabethtown-tires-plus","name":"Tires Plus","slug":"ky-elizabethtown-tires-plus","lat":37.7013429,"lng":-85.8687888,"state":"KY","city":"Elizabethtown","address":"514 West Dixie Avenue","zip":"42701","phone":"+1-270-506-0513","email":"","website":"https://www.tiresplus.com/kentucky/elizabethtown/514-w-dixie-ave/","hours":"","brand":"Tires Plus","services":["tires"],"shopType":"tire_shop"},{"id":"shop-ky-princeton-pro-collision-body-shop","name":"Pro Collision Body Shop","slug":"ky-princeton-pro-collision-body-shop","lat":37.1060379,"lng":-87.952831,"state":"KY","city":"Princeton","address":"11181 US HWY 62 W","zip":"42445","phone":"+1-270-365-2634","email":"","website":"","hours":"","brand":"","services":["body_work"],"shopType":"body_shop"},{"id":"shop-ky-salyersville-isacc-s-wrecker-service","name":"Isacc's Wrecker Service","slug":"ky-salyersville-isacc-s-wrecker-service","lat":37.746372,"lng":-83.0022881,"state":"KY","city":"Salyersville","address":"1220 New Paintsville Road","zip":"41465","phone":"+1-606-349-5728","email":"","website":"","hours":"","brand":"","services":["towing","exhausts","exhaust","body_work"],"shopType":"general_repair"},{"id":"shop-ky-henderson-minors-auto","name":"Minors Auto","slug":"ky-henderson-minors-auto","lat":37.8173044,"lng":-87.5843373,"state":"KY","city":"Henderson","address":"1538 Madison Street","zip":"42420","phone":"","email":"","website":"","hours":"","brand":"","services":["general_repair"],"shopType":"general_repair"},{"id":"shop-ky-elizabethtown-take-5-car-wash-2","name":"Take 5 Car Wash","slug":"ky-elizabethtown-take-5-car-wash-2","lat":37.7076718,"lng":-85.8397867,"state":"KY","city":"Elizabethtown","address":"1001 North Mulberry Street","zip":"42701","phone":"+1 270-918-5092","email":"","website":"https://www.take5carwash.com/locations/kentucky/elizabethtown/49276/","hours":"","brand":"Take 5","services":["general_repair"],"shopType":"general_repair"},{"id":"shop-ky-hartford-westerfield-s-paint-body-shop","name":"Westerfield's Paint & Body Shop","slug":"ky-hartford-westerfield-s-paint-body-shop","lat":37.5280874,"lng":-86.9711318,"state":"KY","city":"Hartford","address":"6321 US Highway 231 N","zip":"42347","phone":"","email":"","website":"","hours":"","brand":"","services":["body_work"],"shopType":"body_shop"},{"id":"shop-ky-corbin-wallens-towing-recovery","name":"Wallens Towing & Recovery","slug":"ky-corbin-wallens-towing-recovery","lat":36.9560431,"lng":-84.0940535,"state":"KY","city":"Corbin","address":"952 West Dixie Highway","zip":"40701","phone":"+1-606-523-1101","email":"wallenstowing@yahoo.com","website":"https://www.wallenstowing.com/","hours":"","brand":"","services":["towing"],"shopType":"general_repair"},{"id":"shop-ky-lexington-valvoline-instant-oil-change-3","name":"Valvoline Instant Oil Change","slug":"ky-lexington-valvoline-instant-oil-change-3","lat":38.0261029,"lng":-84.4084468,"state":"KY","city":"Lexington","address":"2600 Polo Club Boulevard","zip":"","phone":"","email":"","website":"https://store.vioc.com/ky/lexington/oil-change-040209.html","hours":"","brand":"Valvoline","services":["oil_change"],"shopType":"quick_lube"},{"id":"shop-ky-elizabethtown-discount-tire","name":"Discount Tire","slug":"ky-elizabethtown-discount-tire","lat":37.7269004,"lng":-85.8823896,"state":"KY","city":"Elizabethtown","address":"1531 North Dixie Highway","zip":"42701","phone":"","email":"","website":"","hours":"","brand":"Discount Tire","services":["tires"],"shopType":"tire_shop"},{"id":"shop-ky-booneville-ashland","name":"Ashland","slug":"ky-booneville-ashland","lat":37.4770877,"lng":-83.6748558,"state":"KY","city":"Booneville","address":"Mulberry Street","zip":"41314","phone":"","email":"","website":"","hours":"","brand":"","services":["general_repair"],"shopType":"general_repair"},{"id":"shop-ky-adairville-trimble-s-service-center-tire-repair","name":"Trimble's Service Center & Tire Repair","slug":"ky-adairville-trimble-s-service-center-tire-repair","lat":36.6677247,"lng":-86.851927,"state":"KY","city":"Adairville","address":"102 Main Street","zip":"42202","phone":"+12705396741","email":"","website":"","hours":"","brand":"","services":["tires"],"shopType":"tire_shop"},{"id":"shop-ky-fort-campbell-air-assault-auto-skills-center","name":"Air Assault Auto Skills Center","slug":"ky-fort-campbell-air-assault-auto-skills-center","lat":36.6235232,"lng":-87.451537,"state":"KY","city":"Fort Campbell","address":"5300 Airborne Street","zip":"42223","phone":"+1-270-956-1101","email":"","website":"https://campbell.armymwr.com/programs/air-assault-auto","hours":"Mo, Th, Fr 12:30-19:30; Sa, Su 09:00-16:30","brand":"","services":["general_repair"],"shopType":"general_repair"},{"id":"shop-ky-radcliff-jiffy-lube","name":"Jiffy Lube","slug":"ky-radcliff-jiffy-lube","lat":37.8413964,"lng":-85.9389135,"state":"KY","city":"Radcliff","address":"220 North Dixie Boulevard","zip":"40160","phone":"+1-270-801-0167","email":"","website":"https://www.jiffylube.com/locations/ky/radcliff/4111","hours":"Mo 10:00-16:00; Tu-Fr 08:00-19:00; Sa 08:00-17:00","brand":"Jiffy Lube","services":["oil_change"],"shopType":"quick_lube"},{"id":"shop-ky-madisonville-take-5-car-wash","name":"Take 5 Car Wash","slug":"ky-madisonville-take-5-car-wash","lat":37.3482845,"lng":-87.4970678,"state":"KY","city":"Madisonville","address":"3 Chelsea Drive","zip":"42431","phone":"+1 270-214-9729","email":"","website":"https://www.take5.com/locations/car-wash/kentucky/madisonville/45012/","hours":"","brand":"Take 5","services":["general_repair"],"shopType":"general_repair"},{"id":"shop-ky-salyersville-don-s-super-lube","name":"Don's Super Lube","slug":"ky-salyersville-don-s-super-lube","lat":37.733372,"lng":-83.0604537,"state":"KY","city":"Salyersville","address":"1388 Royalton Road","zip":"41465","phone":"+1-606-349-3020","email":"","website":"","hours":"","brand":"","services":["fluid_changes","oil_change"],"shopType":"quick_lube"},{"id":"shop-ky-salyersville-harper-s-auto-repair","name":"Harper's Auto Repair","slug":"ky-salyersville-harper-s-auto-repair","lat":37.7197222,"lng":-83.0490794,"state":"KY","city":"Salyersville","address":"2629 Royalton Road","zip":"41465","phone":"+1-606-349-6717","email":"","website":"","hours":"Mo-Fr 06:30-17:00","brand":"","services":["general_repair"],"shopType":"general_repair"},{"id":"shop-ky-grayson-grayson-automotive","name":"Grayson Automotive","slug":"ky-grayson-grayson-automotive","lat":38.3482602,"lng":-82.9329027,"state":"KY","city":"Grayson","address":"756 C W Stevens Boulevard","zip":"41143","phone":"","email":"","website":"","hours":"","brand":"","services":["general_repair"],"shopType":"general_repair"},{"id":"shop-ky-radcliff-harold-s-auto-service","name":"Harold's Auto Service","slug":"ky-radcliff-harold-s-auto-service","lat":37.8318664,"lng":-85.9303319,"state":"KY","city":"Radcliff","address":"782 South Dixie Boulevard","zip":"40160","phone":"+1-270-351-1469","email":"","website":"","hours":"Mo-Fr 07:30-17:30; Sa-Su off","brand":"","services":["general_repair"],"shopType":"general_repair"},{"id":"shop-ky-radcliff-open-door-auto-sales-and-service","name":"Open Door Auto Sales and Service","slug":"ky-radcliff-open-door-auto-sales-and-service","lat":37.855529,"lng":-85.9531753,"state":"KY","city":"Radcliff","address":"1467 North Dixie Boulevard","zip":"40160","phone":"+1-270-351-2222","email":"","website":"","hours":"","brand":"","services":["general_repair"],"shopType":"general_repair"},{"id":"shop-ky-radcliff-ready-s-automotive-michelin-tire-dealership","name":"Ready's Automotive & Michelin Tire Dealership","slug":"ky-radcliff-ready-s-automotive-michelin-tire-dealership","lat":37.8449877,"lng":-85.9449564,"state":"KY","city":"Radcliff","address":"601 North Wilson Road","zip":"40160","phone":"+1-270-352-3124","email":"","website":"https://www.readysautomotive.com/","hours":"Mo-Fr 08:00-17:30; Sa 09:00-13:00; Su off","brand":"","services":["tires"],"shopType":"tire_shop"},{"id":"shop-ky-radcliff-attention-2-detail","name":"Attention 2 Detail","slug":"ky-radcliff-attention-2-detail","lat":37.8166812,"lng":-85.924769,"state":"KY","city":"Radcliff","address":"1869 South Dixie Boulevard","zip":"40160","phone":"+1-270-801-0163","email":"","website":"","hours":"Mo-Fr 09:00-17:00; Sa 10:00-15:00; Su off","brand":"","services":["general_repair"],"shopType":"general_repair"},{"id":"shop-ky-radcliff-billy-s-towing-and-recovery","name":"Billy's Towing and Recovery","slug":"ky-radcliff-billy-s-towing-and-recovery","lat":37.8197759,"lng":-85.9248848,"state":"KY","city":"Radcliff","address":"1690 South Dixie Boulevard","zip":"40160","phone":"+1-270-421-2331","email":"jbeat96@yahoo.com","website":"","hours":"24/7","brand":"","services":["towing"],"shopType":"general_repair"},{"id":"shop-ky-radcliff-caliber-collision","name":"Caliber Collision","slug":"ky-radcliff-caliber-collision","lat":37.8086754,"lng":-85.9177095,"state":"KY","city":"Radcliff","address":"2878 Centennial Avenue","zip":"40160","phone":"+1-270-600-4560","email":"","website":"https://www.caliber.com/find-a-location/radcliff?","hours":"Mo-Fr 07:30-17:30; Sa-Su off","brand":"Caliber Collision","services":["body_work","body_repair"],"shopType":"body_shop"},{"id":"shop-ky-elizabethtown-milex-complete-auto-care-mr-transmission","name":"Milex Complete Auto Care - Mr. Transmission","slug":"ky-elizabethtown-milex-complete-auto-care-mr-transmission","lat":37.7849695,"lng":-85.9111621,"state":"KY","city":"Elizabethtown","address":"6975 South Dixie Boulevard","zip":"42701","phone":"+1-270-982-2990","email":"","website":"https://milexcompleteautocare.com/elizabethtown-auto/","hours":"","brand":"","services":["transmission"],"shopType":"transmission_shop"},{"id":"shop-ky-elizabethtown-rnr-tire-express","name":"RNR Tire Express","slug":"ky-elizabethtown-rnr-tire-express","lat":37.7102907,"lng":-85.8378347,"state":"KY","city":"Elizabethtown","address":"3045 Dolphin Drive","zip":"42701","phone":"+1-270-600-0022","email":"","website":"https://www.rnrtires.com/","hours":"","brand":"","services":["tires"],"shopType":"tire_shop"},{"id":"shop-ky-henderson-east-side-tire","name":"East Side Tire","slug":"ky-henderson-east-side-tire","lat":37.8211563,"lng":-87.5808233,"state":"KY","city":"Henderson","address":"813 Atkinson Street","zip":"42420","phone":"","email":"","website":"","hours":"","brand":"","services":["tires"],"shopType":"tire_shop"},{"id":"shop-ky-pikeville-road-tested-tire-auto","name":"Road Tested Tire & Auto","slug":"ky-pikeville-road-tested-tire-auto","lat":37.4718943,"lng":-82.5277463,"state":"KY","city":"Pikeville","address":"121 South Mayo Trail","zip":"41501","phone":"","email":"","website":"","hours":"","brand":"","services":["tires"],"shopType":"tire_shop"}]